vidnavigator/__init__.py
vidnavigator/client.py
vidnavigator/exceptions.py
vidnavigator/models.py
vidnavigator-0.1.5.dist-info/licenses/LICENSE
vidnavigator-0.1.5.dist-info/METADATA
vidnavigator-0.1.5.dist-info/WHEEL
vidnavigator-0.1.5.dist-info/top_level.txt
vidnavigator-0.1.5.dist-info/RECORD
