Metadata-Version: 2.4
Name: vidnavigator
Version: 0.1.5
Summary: Python SDK for the VidNavigator Developer API
Author-email: Hatem <hatem.mezlini@vidnavigator.com>
License:                                  Apache License
Project-URL: Homepage, https://vidnavigator.com
Project-URL: Repository, https://github.com/vidnavigator/vidnavigator-python
Project-URL: Bug Tracker, https://github.com/vidnavigator/vidnavigator-python/issues
Classifier: Development Status :: 4 - Beta
Classifier: Intended Audience :: Developers
Classifier: License :: OSI Approved :: Apache Software License
Classifier: Programming Language :: Python :: 3
Classifier: Programming Language :: Python :: 3.7
Classifier: Programming Language :: Python :: 3.8
Classifier: Programming Language :: Python :: 3.9
Classifier: Programming Language :: Python :: 3.10
Classifier: Programming Language :: Python :: 3.11
Classifier: Topic :: Software Development :: Libraries :: Python Modules
Requires-Python: >=3.7
License-File: LICENSE
Requires-Dist: requests>=2.31.0
Requires-Dist: pydantic>=1.10
Dynamic: license-file
